fstop/__init__.py
fstop/engine.py
fstop/pak.py
fstop-0.0.3.dist-info/LICENSE
fstop-0.0.3.dist-info/METADATA
fstop-0.0.3.dist-info/WHEEL
fstop-0.0.3.dist-info/top_level.txt
fstop-0.0.3.dist-info/RECORD
