Metadata-Version: 2.1
Name: fstop
Version: 0.0.3
Summary: The f-stop Engine
Home-page: https://github.com/NoelKaczmarek/fstop
Author: Noel Kaczmarek
Author-email: noel.kaczmarek@gmail.com
License: UNKNOWN
Platform: UNKNOWN
Classifier: Programming Language :: Python :: 3
Classifier: License :: OSI Approved :: MIT License
Classifier: Operating System :: OS Independent
